JoseManuel/__init__.py
PrimoN/__init__.py
pyoperaciones/__init__.py
pyoperaciones/culo.py
FindPrimeN-1.0.dist-info/LICENSE.txt
FindPrimeN-1.0.dist-info/METADATA
FindPrimeN-1.0.dist-info/WHEEL
FindPrimeN-1.0.dist-info/top_level.txt
FindPrimeN-1.0.dist-info/RECORD
