Metadata-Version: 2.1
Name: FindPrimeN
Version: 1.0
Summary: A tool to find prime numbers
Home-page: UNKNOWN
Author: Jose Manuel Iniesta Fernandez
Author-email: jiniesta.fr2@gmail.com
License: GNU GPLv3
Keywords: Prime number searcher
Platform: UNKNOWN
Classifier: Development Status :: 4 - Beta
Classifier: Intended Audience :: Developers
Classifier: License :: OSI Approved :: GNU General Public License v3 (GPLv3)
Classifier: Programming Language :: Python :: 3
Classifier: Operating System :: OS Independent
